bridgebots_sequence/__init__.py
bridgebots_sequence/bidding_context_features.py
bridgebots_sequence/bidding_sequence_features.py
bridgebots_sequence/confusion_evaulation.py
bridgebots_sequence/create_data_splits.py
bridgebots_sequence/create_sequence_examples.py
bridgebots_sequence/dataset_pipeline.py
bridgebots_sequence/drive/MyDrive/bid_learn/models/target_bidding/run_1_checkpoints/keras_metadata.pb
bridgebots_sequence/drive/MyDrive/bid_learn/models/target_bidding/run_1_checkpoints/saved_model.pb
bridgebots_sequence/drive/MyDrive/bid_learn/models/target_bidding/run_1_checkpoints/variables/variables.data-00000-of-00001
bridgebots_sequence/drive/MyDrive/bid_learn/models/target_bidding/run_1_checkpoints/variables/variables.index
bridgebots_sequence/evaluation.py
bridgebots_sequence/evaluation_scratch.py
bridgebots_sequence/feature_utils.py
bridgebots_sequence/inference.py
bridgebots_sequence/interpreter.py
bridgebots_sequence/loss_scratch.py
bridgebots_sequence/model_metadata.py
bridgebots_sequence/sequence_schemas.py
bridgebots_sequence/toy_scratch.py
bridgebots_sequence/train_bidding_lstm.py
bridgebots_sequence/training_utils.py
bridgebots_sequence-0.0.1.dev0.dist-info/WHEEL
bridgebots_sequence-0.0.1.dev0.dist-info/METADATA
bridgebots_sequence-0.0.1.dev0.dist-info/RECORD
